[
    {
        "URL": "https://x.com/ecomarxi",
        "Date": "03/12/2024",
        "Text": " ALL DONATIONS DOUBLED \n\nThis campaign is for people in Gaza without campaigns \u2014 and GlobalGiving will match any donations made until midnight tonight!\n\nThat means all donations are doubled!\n\nPlease donate if you can!\n\nhttps://gofund.me/a385b712",
        "Weight": 4,
        "Id": 2
    },
    {
        "URL": "https://x.com/MothTongue_/status/1863945664272400862",
        "Date": "03/12/2024",
        "Text": "approximately 163.5k dollars needed for \n@munigaza\n's vital life-making infrastructure initiative! \n\nthe question STILL remains:\n \n\"ARE WE SERIOUS PEOPLE!?\"\n\nWE ONLY HAVE 21 DAYS \nTO FULFILL THIS, TO PROVE IT!!\n\nWE STILL NEED \n**EVERY** \nVOICE NOW!!! \n\nhttps://gaza-city.ensany.com/campaign/6737",
        "Weight": 8,
        "Id": 3
    },
    {
        "URL": "https://x.com/MintPressNews/status/1863921011315376562",
        "Date": "03/12/2024",
        "Text": "A new MintPress News study has unearthed a network of former agents of Israeli spying agency, Unit 8200 working at TikTok, a company charged with supposedly being a Chinese-owned hub of anti-Semitic content.",
        "Weight": 8,
        "Id": 4
    },
    {
        "URL": "https://x.com/ecomarxi/status/1863935481525703133",
        "Date": "03/12/2024",
        "Text": " ALL DONATIONS DOUBLED \n\nThis campaign is for people in Gaza without campaigns \u2014 and GlobalGiving will match any donations made until midnight tonight!\n\nThat means all donations are doubled!\n\nPlease donate if you can!\n\nhttps://gofund.me/a385b712",
        "Weight": 4,
        "Id": 5
    },
    {
        "URL": "https://x.com/AssalRad/status/1863667048540409867",
        "Date": "02/12/2024",
        "Text": ": Good news! We brokered a \u201cceasefire\u201d in Lebanon\n\n: We can still attack if we want\n\nUN: Israel breached the ceasefire 100 times\n\nHezbollah: We\u2019re responding to Israel\u2019s violations\n\n: Hezbollah breached the ceasefire! We\u2019re attacking\n\n: Israel has a right to defend itself",
        "Weight": 18,
        "Id": 6
    },
    {
        "URL": "https://x.com/ecomarxi",
        "Date": "02/12/2024",
        "Text": "Israel\u2019s plan is obviously to follow what the US done to Native Americans: kill as many as they need to, forcing them into smaller and smaller areas of land, until eventually the only viable solution is a single state with total control.\n\nAnd nobody can say they didn\u2019t know.",
        "Weight": 4,
        "Id": 7
    },
    {
        "URL": "https://x.com/ecomarxi/status/1863913464458002466",
        "Date": "03/12/2024",
        "Text": "Imagine thinking the year Israel committed the most public genocide in world history was the right time for Labour to publicly embrace Israeli lobbyists",
        "Weight": 17,
        "Id": 9
    },
    {
        "URL": "https://x.com/AsaWinstanley/status/1863648853209026677",
        "Date": "02/12/2024",
        "Text": "Spotted in the background of this photo from the psychopathic Labour Friends of Israel annual dinner -- Jake Wallis Simons, the Islamophobic editor of obsessively anti-Palestinian newspaper The Jewish Chronicle (which has for decades laundered Israeli government lies).",
        "Weight": 20,
        "Id": 10
    },
    {
        "URL": "https://x.com/ScottishCommie/status/1862325327550111844",
        "Date": "29/11/2024",
        "Text": "Palestinians are on this site. Many beg to be saved, for donations just so they can afford a bag of flour. They've documented this genocide in the hopes someone will stop it. We can't let them be abandoned. Liberation is possible. We have to help.",
        "Weight": 13,
        "Id": 13
    },
    {
        "URL": "https://x.com/ecomarxi/status/1863865850081509463",
        "Date": "03/12/2024",
        "Text": " PLEASE READ - MATCHED DONATION DAY \n\nThis campaign is for people in Gaza without campaigns \u2014 and GlobalGiving will match any donations made until midnight EST tonight!\n\nThat means all donations are double!\n\nPlease share and donate if you can!",
        "Weight": 4,
        "Id": 14
    },
    {
        "URL": "https://x.com/ecomarxi/status/1863726405416083591",
        "Date": "02/12/2024",
        "Text": "The genocide in Gaza continues. Isreal is still using US weapons to massacre civilians. The scale of horror and devastation will likely take years to fully uncover so we must not stop speaking out every single day. https://x.com/malcolm_pal9/s/malcolm_pal9/status/1863660952425521431\u2026",
        "Weight": 9,
        "Id": 17
    },
    {
        "URL": "https://x.com/ecomarxi/status/1863703332616847727",
        "Date": "02/12/2024",
        "Text": "\u201cNobody is above the law,\u201d said the man committing genocide, threatening the International Criminal Court for his allies, pardoning his criminal son and using propaganda to lie about it all",
        "Weight": 5,
        "Id": 20
    },
    {
        "URL": "https://x.com/ecomarxi/status/1863702536068137203",
        "Date": "02/12/2024",
        "Text": "Israel targeting people who feed the starving in Gaza is just one of a thousand different ways they reveal their intentions to make Gaza uninhabitable so they can ethnically cleanse it.\n\nMore war crimes, more innocents killed, just another day for Israel.",
        "Weight": 28,
        "Id": 22
    },
    {
        "URL": "https://x.com/ecomarxi/status/1863700390467752071",
        "Date": "02/12/2024",
        "Text": "CNN has just reported that Israel has violated the ceasefire deal with Lebanon \u201cabout 100 times.\u201d Nothing Israel says can ever be trusted \u2014 nothing. Everything is a lie carefully designed to manufacture consent for the Greater Israel colonial project with full Western support.",
        "Weight": 12,
        "Id": 24
    },
    {
        "URL": "https://x.com/ecomarxi/status/1863696284751655404",
        "Date": "02/12/2024",
        "Text": "Opposing the vast and immeasurable crimes of the United States Empire in its perpetual violent pursuit of greater and greater resources as it swallows the earth and destroys everything from families to forests to our very future does not require supporting every regime it attacks",
        "Weight": 2,
        "Id": 25
    },
    {
        "URL": "https://x.com/ecomarxi/status/1863685357843222827",
        "Date": "02/12/2024",
        "Text": "Israel\u2019s plan is obviously to follow what the US done to Native Americans: kill as many as they need to, forcing them into smaller and smaller areas of land, until eventually the only viable solution is a single state with total control.\n\nAnd nobody can say they didn\u2019t know.",
        "Weight": 4,
        "Id": 31
    },
    {
        "URL": "https://x.com/Ema97n/status/1863679000976986462",
        "Date": "02/12/2024",
        "Text": "Meanwhile, Israel is ethnically cleansing Palestinian Christians in Gaza..",
        "Weight": 12,
        "Id": 33
    },
    {
        "URL": "https://x.com/jasonhickel/status/1863611983972487410",
        "Date": "02/12/2024",
        "Text": "The United States is now waging proxy wars against no fewer than three countries in Eurasia while arming and funding a genocide against a fourth.",
        "Weight": 5,
        "Id": 35
    },
    {
        "URL": "https://x.com/MothTongue_/status/1863593494918353099",
        "Date": "02/12/2024",
        "Text": "approximately 164k dollars needed for \n@munigaza\n's vital life-making infrastructure initiative! \n\nthe question STILL remains:\n \n\"ARE WE SERIOUS PEOPLE!?\"\n\nWE ONLY HAVE 22 DAYS \nTO FULFILL THIS, TO PROVE IT!!\n\nWE STILL NEED \n**EVERY** \nVOICE NOW!!! \n\nhttps://gaza-city.ensany.com/campaign/6737",
        "Weight": 8,
        "Id": 38
    },
    {
        "URL": "https://x.com/chai_zaferooni/status/1863597614954147973",
        "Date": "02/12/2024",
        "Text": "Mohammed is only $350 away from reaching half of his goal. He & his family are trying to survive the Holocaust in jabaliya. He is also injured in his leg & needs specialized surgery. Who can help him reach $12500 today? \n\nhttps://gofundme.com/f/help-mohammeds-family-through-gaza-crisis\u2026",
        "Weight": 7,
        "Id": 40
    },
    {
        "URL": "https://x.com/Ema97n/status/1863582167638417886",
        "Date": "02/12/2024",
        "Text": "This is literally how genocide happens, insisting to kill innocents\u2014Mr 'it still found her' \n@BBCWorld",
        "Weight": 5,
        "Id": 42
    },
    {
        "URL": "https://x.com/sahouraxo/status/1863429919742505144",
        "Date": "02/12/2024",
        "Text": "62.\n\nThat\u2019s how many times Israel has violated the so-called \u201cceasefire\u201d in Lebanon\u2014just in the past 5 days.\n\n\u201cThis is the worst ceasefire you could possibly imagine; where one side is allowed to fire and the other side is not allowed to fire back.\u201d",
        "Weight": 4,
        "Id": 45
    },
    {
        "URL": "https://x.com/ecomarxi",
        "Date": "01/12/2024",
        "Text": "A \u2018ceasefire\u2019 is when Israel bombs Lebanon but Lebanon doesn\u2019t retaliate, apparently",
        "Weight": 4,
        "Id": 48
    },
    {
        "URL": "https://x.com/jennineak/status/1862959205256237512",
        "Date": "30/11/2024",
        "Text": "Also Matt Bilinsky of law firm Weinberg Gosner.\n\n1. \u2018There are no schools in Gaza left \u2019\n2. Laughs about how \u2018nothing\u2019s going to happen\u2019 to genocide supporters\u2014 clearly used to impunity \n3. Mocks Palestinians in Gaza again\n4. Calls a Jewish ethnostate a superior civilisation",
        "Weight": 25,
        "Id": 51
    },
    {
        "URL": "https://x.com/StopArabHate/status/1862852131532710263",
        "Date": "30/11/2024",
        "Text": " \u201cYou come from a loser 3rd world civilization of peasants and terrorists and will always be a step behind\u201d\n\n- Matt Bilinsky, LA-based attorney at Weinberg Gosner LLP",
        "Weight": 10,
        "Id": 52
    },
    {
        "URL": "https://x.com/ecomarxi/status/1863371506765447183",
        "Date": "01/12/2024",
        "Text": "A \u2018ceasefire\u2019 is when Israel bombs Lebanon but Lebanon doesn\u2019t retaliate, apparently",
        "Weight": 4,
        "Id": 56
    },
    {
        "URL": "https://x.com/ecomarxi",
        "Date": "01/12/2024",
        "Text": " FAMILY IN GAZA IN URGENT NEED \n\nMohammed\u2019s campaign has been verified by Palestinians in the diaspora, and he is living in Northern Gaza in desperate need of help for him and his family.\n\nIf you can, please donate \u2014 and share!",
        "Weight": 16,
        "Id": 57
    },
    {
        "URL": "https://x.com/ousmannoor/status/1863232227405926436",
        "Date": "01/12/2024",
        "Text": "It needs to end.\n\nEstablish an international military force now to protect civilians, ensure unhindered aid and guarantee Palestinian self determination.\n\nThe alternative is extermination.\n\nSign and share the petition",
        "Weight": 4,
        "Id": 61
    },
    {
        "URL": "https://x.com/ecomarxi",
        "Date": "01/12/2024",
        "Text": "The most documented genocide in history",
        "Weight": 5,
        "Id": 62
    },
    {
        "URL": "https://x.com/MothTongue_/status/1863219191236415736",
        "Date": "01/12/2024",
        "Text": "approximately 165k dollars needed for \n@munigaza\n's vital life-making infrastructure initiative! \n\nthe question STILL remains:\n \n\"ARE WE SERIOUS PEOPLE!?\"\n\nWE ONLY HAVE 23 DAYS \nTO FULFILL THIS, TO PROVE IT!!\n\nWE STILL NEED \n**EVERY** \nVOICE NOW!!! \n\nhttps://gaza-city.ensany.com/campaign/6737",
        "Weight": 8,
        "Id": 66
    },
    {
        "URL": "https://x.com/ecomarxi/status/1863279818822877229",
        "Date": "01/12/2024",
        "Text": "Former Israeli \u2018Defence\u2019 Minister Moshe Ya\u2019alon has clearly stated that Israel is ethnically cleansing Gaza.\n\nWe all know it \u2014 now they\u2019re admitting it.\n\nThis is a campaign of ethnic cleansing and genocide by Israel and the West, nothing less.",
        "Weight": 25,
        "Id": 68
    },
    {
        "URL": "https://x.com/owenjonesjourno/status/1862948988682428736",
        "Date": "30/11/2024",
        "Text": "From the start, those of us who opposed Israel's genocidal onslaught pointed to ethnic cleansing.\n\nWe were smeared and attacked as a result.\n\nHere's what I said on 13th October 2023.\n\nIsrael's former army chief now says it's ethnic cleansing.\n\nEverything we said was right.",
        "Weight": 8,
        "Id": 70
    },
    {
        "URL": "https://x.com/ecomarxi/status/1863231772722450650",
        "Date": "01/12/2024",
        "Text": "The most documented genocide in history",
        "Weight": 5,
        "Id": 71
    },
    {
        "URL": "https://x.com/richimedhurst/status/1863192296700743736",
        "Date": "01/12/2024",
        "Text": "You've seen how the media lie non-stop about Gaza.\n\nBut when it comes to Syria you believe them? \n\nLol. \n\nDid you think Israel, US. Turkey and their \"moderate rebels\" linked to Al Qaeda are occupying more than 1/3 of Syria and stealing its oil and crops for a good cause?",
        "Weight": 8,
        "Id": 73
    },
    {
        "URL": "https://x.com/ecomarxi",
        "Date": "30/11/2024",
        "Text": "Any argument that Western society was worth saving died this year with over 200k Palestinians",
        "Weight": 8,
        "Id": 74
    },
    {
        "URL": "https://x.com/mehdirhasan/status/1862317326994927716",
        "Date": "29/11/2024",
        "Text": "Children in Gaza are starving right now because of your vetoes at the UN.",
        "Weight": 4,
        "Id": 76
    },
    {
        "URL": "https://x.com/ecomarxi/status/1862911950918652063",
        "Date": "30/11/2024",
        "Text": "Any argument that Western society was worth saving died this year with over 200k Palestinians",
        "Weight": 8,
        "Id": 78
    },
    {
        "URL": "https://x.com/_ZachFoster/status/1862883105759015176",
        "Date": "30/11/2024",
        "Text": "\u2014signed, Israel, a nation-state created through the process of ethnically cleansing  the people that lived in Palestine before Zionists colonized it",
        "Weight": 18,
        "Id": 80
    },
    {
        "URL": "https://x.com/ecomarxi/status/1862911014401958190",
        "Date": "30/11/2024",
        "Text": "This verified campaign is to help Mohammed take care of his mother, as well as medical help for his injured leg.\n\nI know many are in need, but if you\u2019re able to support his family in their efforts to survive in Gaza, please do so!\n\n",
        "Weight": 4,
        "Id": 81
    },
    {
        "URL": "https://x.com/chai_zaferooni/status/1862906938175914405",
        "Date": "30/11/2024",
        "Text": "Mohammed is only $1522 away from reaching half of his goal\u2014 which is a significant milestone considering he had no donations at all in the beginning of this month. His family is trying to survive the Holocaust in jabaliya & Mohammed needs specialized surgery on his foot.",
        "Weight": 3,
        "Id": 84
    },
    {
        "URL": "https://x.com/ecomarxi/status/1862908976410525759",
        "Date": "30/11/2024",
        "Text": "This is insane\u2026\n\nSydney police: There is antisemitic material in the car\n\nPerson: What is the antisemitic material?\n\nPolice: There is a small image of a watermelon\n\n",
        "Weight": 6,
        "Id": 86
    },
    {
        "URL": "https://x.com/ecomarxi",
        "Date": "30/11/2024",
        "Text": "Biden buying a book on the colonisation of Palestine after committing genocide on the Palestinians to perpetuate that colonisation is perhaps the perfect representation of the hollow virtue and sheer ignorance of liberalism in all of history",
        "Weight": 17,
        "Id": 88
    },
    {
        "URL": "https://x.com/BasharZapen/status/1862540719317033213",
        "Date": "29/11/2024",
        "Text": "In less than 14 months, we went through: \n\n\u201cIsrael is acting according to international law.\u201d\n\n\u201cIsrael is not violating international law because\u2026\u201d\n\n\u201cInternational law doesn't apply to Israel because\u2026\u201d\n\n\u201cInternational law must be abolished because of Israel.\u201d",
        "Weight": 16,
        "Id": 90
    },
    {
        "URL": "https://x.com/zei_squirrel/status/1862708828912902163",
        "Date": "30/11/2024",
        "Text": "Israeli occupation troops in Gaza found a Jewish cemetery for soldiers killed in WW1, maintained in pristine condition in the \"Hamas-run Gaza\". And they proudly posted photo-ops in front of it without even realizing it undermines their main propaganda about Hamas",
        "Weight": 33,
        "Id": 91
    },
    {
        "URL": "https://x.com/ecomarxi/status/1862797483673354451",
        "Date": "30/11/2024",
        "Text": "Biden buying a book on the colonisation of Palestine after committing genocide on the Palestinians to perpetuate that colonisation is perhaps the perfect representation of the hollow virtue and sheer ignorance of liberalism in all of history",
        "Weight": 17,
        "Id": 92
    },
    {
        "URL": "https://x.com/codepink/status/1862530996207259809",
        "Date": "29/11/2024",
        "Text": "Overnight, Israel killed more than 40 Palestinians in attacks across Gaza.\n\nOver 137 people have also been injured.\n\nBiden is set to send $680 million more in weapons to Israel.\n\nIn his last days in office, Genocide Joe is fast-tracking more killing.",
        "Weight": 25,
        "Id": 94
    },
    {
        "URL": "https://x.com/ousmannoor/status/1862599110848590256",
        "Date": "29/11/2024",
        "Text": "Israel will continue to exterminate Palestinians.\n\nThe ONLY way to stop the genocide is to establish an international military force to protect Palestinian civilians, ensure unhindered aid and guarantee self determination.\n\nSign and share the petition:",
        "Weight": 21,
        "Id": 96
    },
    {
        "URL": "https://x.com/ecomarxi/status/1862598698754093183",
        "Date": "29/11/2024",
        "Text": "Israel\u2019s goal is to kill as many Palestinians as possible \u2014 directly with weapons or indirectly via a manufactured humanitarian crisis \u2014 while pretending they are \u2018fighting Hamas.\u2019\n\nThis grants their Western backers plausible deniability over the ongoing genocide.",
        "Weight": 21,
        "Id": 97
    },
    {
        "URL": "https://x.com/ecomarxi/status/1862591553950089325",
        "Date": "29/11/2024",
        "Text": "Please \u2014 if you are able to help, Mohammed\u2019s campaign has been verified, he is living in Northern Gaza in terrible conditions, and him and his family are desperate for support for their basic needs.\n\nThank you ",
        "Weight": 4,
        "Id": 101
    },
    {
        "URL": "https://x.com/chai_zaferooni/status/1862530917111132305",
        "Date": "29/11/2024",
        "Text": "Jummah mubarak! Please consider donating to Gazans instead of buying unnecessary things on Black Friday. Mohammed & his family are trying to survive the Holocaust in jabaliya & are close to reaching half of their goal. he is injured in his leg & needs specialized surgery.",
        "Weight": 7,
        "Id": 102
    },
    {
        "URL": "https://x.com/MothTongue_/status/1862554734147600430",
        "Date": "29/11/2024",
        "Text": "approximately 170k dollars needed for \n@munigaza\n's vital life-making infrastructure initiative! \n\nthe question STILL remains:\n \n\"ARE WE SERIOUS PEOPLE!?\"\n\nWE ONLY HAVE 25 DAYS \nTO FULFILL THIS, TO PROVE IT!!\n\nWE STILL NEED \n**EVERY** \nVOICE NOW!!! \n\nhttps://gaza-city.ensany.com/campaign/6737",
        "Weight": 8,
        "Id": 103
    },
    {
        "URL": "https://x.com/iamjourjean/status/1862429118421172263",
        "Date": "29/11/2024",
        "Text": "Adolf Hitler in 1943:",
        "Weight": 1,
        "Id": 105
    },
    {
        "URL": "https://x.com/Imran_posts/status/1862471930676195831",
        "Date": "29/11/2024",
        "Text": "NEW: The Oxford Union has voted that \"Israel is an apartheid state responsible for genocide\" by an overwhelming majority of 278 to 59",
        "Weight": 9,
        "Id": 108
    },
    {
        "URL": "https://x.com/jennineak/status/1862411503871435246",
        "Date": "29/11/2024",
        "Text": "The \u2018doxxing\u2019 in question was a leak of a racist WhatsApp group chat of hundreds of Jewish Australians in the arts/creative/media space plotting to destroy the livelihoods of Palestinian creatives and allies. Love a good Amsterdam spin where the culprits are the victims ",
        "Weight": 8,
        "Id": 109
    },
    {
        "URL": "https://x.com/CraigMurrayOrg/status/1862379693908877332",
        "Date": "29/11/2024",
        "Text": "I have a heartfelt plea to my fellow Scots.\nFor God's sake, there is a most appalling genocide in progress and the London government is actively complicit - both Tory and Labour.\nNow is the time to reject inhumanity and stand up for decency by declaring and taking Independence.",
        "Weight": 5,
        "Id": 113
    },
    {
        "URL": "https://x.com/ecomarxi",
        "Date": "28/11/2024",
        "Text": "What?! You\u2019re telling me that the country that celebrates its own genocide, ethnic cleansing and land theft as a national holiday supports genocide, ethnic cleansing and land theft as foreign policy? No way!",
        "Weight": 10,
        "Id": 115
    },
    {
        "URL": "https://x.com/chai_zaferooni/status/1862170338248835344",
        "Date": "28/11/2024",
        "Text": "Mohammed is seriously injured in his leg & needs a specialized surgery. Famine is more severe in the north & jabaliya has been undergoing intense siege for 2 months. Today is thanksgiving & many people will be feasting as Gazans starve. Please consider matching my $20 donation.",
        "Weight": 4,
        "Id": 119
    },
    {
        "URL": "https://x.com/ecomarxi",
        "Date": "28/11/2024",
        "Text": "The US went from \u201cIsrael is committed to international law\u201d to \u201cinternational law does not apply to Israel or any of us for that matter\u201d in less than a year.\n\nThis is how hyper-normalisation works.",
        "Weight": 8,
        "Id": 121
    },
    {
        "URL": "https://x.com/ecomarxi",
        "Date": "27/11/2024",
        "Text": "This verified campaign for \n@moabuhabble\n is to help him take care of his mother, as well as medical help for his injured leg.\n\nI know many are in need, but if you\u2019re able to support his family in their efforts to survive in Gaza, please do so!\n\n",
        "Weight": 4,
        "Id": 123
    },
    {
        "URL": "https://x.com/ecomarxi/status/1862182287766413769",
        "Date": "28/11/2024",
        "Text": "The US went from \u201cIsrael is committed to international law\u201d to \u201cinternational law does not apply to Israel or any of us for that matter\u201d in less than a year.\n\nThis is how hyper-normalisation works.",
        "Weight": 8,
        "Id": 126
    },
    {
        "URL": "https://x.com/ecomarxi/status/1862175405945331834",
        "Date": "28/11/2024",
        "Text": "There is an implicit admission within the West\u2019s acceptance and defence of Israel\u2019s crimes \u2014 like mass rape, torturing hostages to death, and gleefully massacring children \u2014 that shows human life and human suffering do not matter to those in charge.\n\nThis is a threat to us all.",
        "Weight": 6,
        "Id": 127
    },
    {
        "URL": "https://x.com/ecomarxi",
        "Date": "28/11/2024",
        "Text": "\u201cThe Rome Statute doesn\u2019t apply to Israel, or the United States, or France, or Germany, or Great Britain, because it wasn\u2019t conceived of to come after us.\u201d\n\n\u2014 Lindsey Graham admits Int\u2019l Law is a tool of Western supremacy that does not apply to the West",
        "Weight": 4,
        "Id": 137
    },
    {
        "URL": "https://x.com/ecomarxi/status/1862104277650379231",
        "Date": "28/11/2024",
        "Text": "What?! You\u2019re telling me that the country that celebrates its own genocide, ethnic cleansing and land theft as a national holiday supports genocide, ethnic cleansing and land theft as foreign policy? No way!",
        "Weight": 10,
        "Id": 140
    },
    {
        "URL": "https://x.com/ecomarxi/status/1862064708120953001",
        "Date": "28/11/2024",
        "Text": "\u201cThe Rome Statute doesn\u2019t apply to Israel, or the United States, or France, or Germany, or Great Britain, because it wasn\u2019t conceived of to come after us.\u201d\n\n\u2014 Lindsey Graham admits Int\u2019l Law is a tool of Western supremacy that does not apply to the West",
        "Weight": 4,
        "Id": 141
    },
    {
        "URL": "https://x.com/ecomarxi/status/1861928768446619930",
        "Date": "28/11/2024",
        "Text": "If you can, please donate to Mohammed\u2019s campaign.\n\nThis has been verified \u2014 he is in Gaza and in dire need of help for him and his family.\n\nThanks ",
        "Weight": 4,
        "Id": 142
    },
    {
        "URL": "https://x.com/ejmalrai/status/1861762727951188100",
        "Date": "27/11/2024",
        "Text": "#Israel has always asked the #US to come and rescue it when it fails to achieve its goals and has always accepted a ceasefire when it's struggling.",
        "Weight": 4,
        "Id": 153
    },
    {
        "URL": "https://x.com/bts_promisa/status/1861400382305382563",
        "Date": "26/11/2024",
        "Text": "We still need \u20ac65 to reach our goal for flour for my family.\nPlease d0nate/share \nhttp://gofund.me/3ef09898\n\n\n@tastefullysaucy\n \n@dahieh48\n \n@cometflesh\n \n@fiona_lone\n \n@gazafunds\n \n@gazafunds\n \n@Shepherds4Good\n \n@ecomarxi\n \n@ARMY4Palestine\n \n@Louis_Allday\n \n\n@IbnRiad\n \n@BIG__Brother7",
        "Weight": 12,
        "Id": 154
    },
    {
        "URL": "https://x.com/respeak_uk/status/1861723280702390503",
        "Date": "27/11/2024",
        "Text": "Seeing so many Palestinians being happy for Lebanon while they are still being genocided.\n\nAmazing people.",
        "Weight": 13,
        "Id": 155
    },
    {
        "URL": "https://x.com/ecomarxi/status/1861738155759583251",
        "Date": "27/11/2024",
        "Text": "This verified campaign for \n@moabuhabble\n is to help him take care of his mother, as well as medical help for his injured leg.\n\nI know many are in need, but if you\u2019re able to support his family in their efforts to survive in Gaza, please do so!\n\n",
        "Weight": 4,
        "Id": 156
    },
    {
        "URL": "https://x.com/ecomarxi",
        "Date": "26/11/2024",
        "Text": "The US gov is now throwing the First Amendment out of the window to protect Israel. They are removing the right to free speech and free assembly if either are used to criticise GENOCIDE, APARTHEID and ETHNIC CLEANSING. The people making these decisions are the enemies of us all.",
        "Weight": 9,
        "Id": 157
    },
    {
        "URL": "https://x.com/kennardmatt/status/1861369741379543222",
        "Date": "26/11/2024",
        "Text": "A UK Shadow R1 spy plane leaves the British base on Cyprus at 6pm last night.\n\nIt was over Gaza for 5 hours collecting intelligence, which is then handed to Israel. \n\nShadow R1\u2019s capabilities include \u2018target acquisition\u2019 for military strikes.\n\nTake note \n@IntlCrimCourt",
        "Weight": 8,
        "Id": 159
    },
    {
        "URL": "https://x.com/jasonhickel/status/1861523115244716398",
        "Date": "26/11/2024",
        "Text": "The NYT headline reads \"Surviving Gaza\"... as if Gaza is maiming people. Zero mention of Israel. I cannot express how obscene this is.",
        "Weight": 12,
        "Id": 161
    },
    {
        "URL": "https://x.com/ecomarxi/status/1861541859161420119",
        "Date": "26/11/2024",
        "Text": "The US gov is now throwing the First Amendment out of the window to protect Israel. They are removing the right to free speech and free assembly if either are used to criticise GENOCIDE, APARTHEID and ETHNIC CLEANSING. The people making these decisions are the enemies of us all.",
        "Weight": 9,
        "Id": 166
    },
    {
        "URL": "https://x.com/RaniaKhalek/status/1861424545271365655",
        "Date": "26/11/2024",
        "Text": "Israel ahead of a potential ceasefire causing as much damage as possible.",
        "Weight": 4,
        "Id": 168
    },
    {
        "URL": "https://x.com/zei_squirrel/status/1861210359761076360",
        "Date": "26/11/2024",
        "Text": "when Anthony Bourdain said free Palestine and called out the racist vilification of Palestinians by the media and political class: \"The world has visited many terrible things on the Palestinian people, none more shameful than robbing them of their basic humanity.\"",
        "Weight": 16,
        "Id": 170
    },
    {
        "URL": "https://x.com/MothTongue_/status/1861076907845943551",
        "Date": "25/11/2024",
        "Text": "approximately 174k dollars needed for \n@munigaza\n's vital life-making infrastructure initiative! \n\nthe question STILL remains:\n \n\"ARE WE SERIOUS PEOPLE!?\"\n\nWE ONLY HAVE 29 DAYS \nTO FULFILL THIS, TO PROVE IT!!\n\nWE STILL NEED \n**EVERY** \nVOICE NOW!!! \n\nhttps://gaza-city.ensany.com/campaign/6737",
        "Weight": 8,
        "Id": 172
    },
    {
        "URL": "https://x.com/caitoz/status/1861162596675789009",
        "Date": "25/11/2024",
        "Text": "Miller is here essentially saying \"Palestinians aren't entitled to protection under international law because we successfully stopped the creation of a Palestinian state.\"",
        "Weight": 12,
        "Id": 173
    },
    {
        "URL": "https://x.com/ecomarxi/status/1861030995064979943",
        "Date": "25/11/2024",
        "Text": "This family of 14 living in Khan Yunes in a tent are desperate for supplies amidst the Israeli siege.\n\nThis campaign has been verified by someone who knows the family and works with human rights bodies. Please support if you can!",
        "Weight": 8,
        "Id": 183
    },
    {
        "URL": "https://x.com/owenjonesjourno/status/1860746745694539985",
        "Date": "24/11/2024",
        "Text": "Israel is allying to ISIS affiliated criminal gangs to starve Gaza.\n\nYou can read about this in the Israeli press.\n\nWhy isn't this splashed on front pages in the West?\n\nNew post ",
        "Weight": 16,
        "Id": 188
    },
    {
        "URL": "https://x.com/ecomarxi",
        "Date": "23/11/2024",
        "Text": "This family of 14 living in Khan Yunes in a tent are desperate for supplies amidst the Israeli siege.\n\nThis campaign has been verified by someone who knows the family and works with human rights bodies. Please support if you can!",
        "Weight": 8,
        "Id": 191
    },
    {
        "URL": "https://x.com/swilkinsonbc/status/1860648989210607648",
        "Date": "24/11/2024",
        "Text": "The UK military sent disturbing messages to editors, saying: don't publish ANY details about UK special forces being in Gaza | via \n@themuslimvoteuk",
        "Weight": 4,
        "Id": 195
    },
    {
        "URL": "https://x.com/ecomarxi/status/1860689662953607533",
        "Date": "24/11/2024",
        "Text": "Israel is losing the main thing that keeps it alive: the cult-like conditioning of Zionism",
        "Weight": 4,
        "Id": 199
    },
    {
        "URL": "https://x.com/ecomarxi",
        "Date": "23/11/2024",
        "Text": "If you\u2019re still defending Israel, you\u2019re what\u2019s wrong with the world",
        "Weight": 4,
        "Id": 203
    },
    {
        "URL": "https://x.com/ecomarxi/status/1860485470670541210",
        "Date": "24/11/2024",
        "Text": "Much of the justification for creating the International Criminal Court was the fact that Nazi Germany committed genocide.\n\nThat Germany has now said it will defy the court to continue committing genocide shows that Nazi Germany is still alive and well.",
        "Weight": 14,
        "Id": 204
    },
    {
        "URL": "https://x.com/EgyptsBeer/status/1860459208027554079",
        "Date": "23/11/2024",
        "Text": "bigger empires have died for smaller crimes",
        "Weight": 2,
        "Id": 205
    },
    {
        "URL": "https://x.com/ecomarxi",
        "Date": "24/11/2024",
        "Text": "Says the guy who supports billions from the same tax dollars being sent to Israel to murder children. \n\nBut yeah, of course, the air conditioning and heating is the real evil you oppose.\n\nIt\u2019s ludicrous how fucking vile your worldview is.",
        "Weight": 4,
        "Id": 207
    },
    {
        "URL": "https://x.com/ecomarxi/status/1860393765313163766",
        "Date": "23/11/2024",
        "Text": "If you\u2019re still defending Israel, you\u2019re what\u2019s wrong with the world",
        "Weight": 4,
        "Id": 208
    },
    {
        "URL": "https://x.com/ecomarxi",
        "Date": "23/11/2024",
        "Text": "Israel just brought down a full residential apartment block in the Basta area in Beirut without warning, at 4am in the morning. Families sleeping soundly in their beds, to wake as their ceilings collapsed in on them.\n\nThis is the US-Israel axis of evil at play",
        "Weight": 8,
        "Id": 209
    },
    {
        "URL": "https://x.com/MothTongue_/status/1860320472354742416",
        "Date": "23/11/2024",
        "Text": "approximately 175k dollars needed for \n@munigaza\n's vital life-making infrastructure initiative! \n\nthe question still remains:\n \n\"ARE WE SERIOUS PEOPLE!?\"\n\nWE ONLY HAVE 31 DAYS \nTO FULFILL THIS, TO PROVE IT!!\n\nWE NEED **EVERY** VOICE NOW!!!\nhttps://gaza-city.ensany.com/campaign/6737",
        "Weight": 8,
        "Id": 210
    },
    {
        "URL": "https://x.com/ecomarxi/status/1860318089604161833",
        "Date": "23/11/2024",
        "Text": "This family of 14 living in Khan Yunes in a tent are desperate for supplies amidst the Israeli siege.\n\nThis campaign has been verified by someone who knows the family and works with human rights bodies. Please support if you can!",
        "Weight": 8,
        "Id": 212
    },
    {
        "URL": "https://x.com/ecomarxi",
        "Date": "23/11/2024",
        "Text": "You\u2019re funding intentional famine in Gaza right now you raging piece of shit.\n\n\u201cToday we remember a heinous crime that we are right now, ourselves committing.\u201d\n\nThis arrogance and hypocrisy will be the end of your Empire of Death.",
        "Weight": 4,
        "Id": 215
    },
    {
        "URL": "https://x.com/MyriamFrancoisC/status/1860306741209989424",
        "Date": "23/11/2024",
        "Text": "\u00ab\u00a0It would be an easy way to dispose of him if Israelies themselves gave him up for arrest\u00a0\u00bb - allies where you at?",
        "Weight": 8,
        "Id": 216
    },
    {
        "URL": "https://x.com/ecomarxi",
        "Date": "22/11/2024",
        "Text": "This verified campaign for \n@moabuhabble\n is desperate for support.\n\nHe has an injured leg and needs medical assistance, as well as basic necessities for him and his family as they live under bombardment in Northern Gaza.\n\nPlease help if you can!",
        "Weight": 4,
        "Id": 217
    },
    {
        "URL": "https://x.com/ecomarxi/status/1860283735574216971",
        "Date": "23/11/2024",
        "Text": "Israel just brought down a full residential apartment block in the Basta area in Beirut without warning, at 4am in the morning. Families sleeping soundly in their beds, to wake as their ceilings collapsed in on them.\n\nThis is the US-Israel axis of evil at play",
        "Weight": 8,
        "Id": 220
    },
    {
        "URL": "https://x.com/MarocBds/status/1860082112097058859",
        "Date": "22/11/2024",
        "Text": "Freedom for Ismail LGHAZAOUI\n\nNo to the criminalization of solidarity with the Palestinian people\n#Free_Ismail_Lghazaoui",
        "Weight": 4,
        "Id": 223
    },
    {
        "URL": "https://x.com/ecomarxi/status/1860092360451064318",
        "Date": "22/11/2024",
        "Text": "This verified campaign for \n@moabuhabble\n is desperate for support.\n\nHe has an injured leg and needs medical assistance, as well as basic necessities for him and his family as they live under bombardment in Northern Gaza.\n\nPlease help if you can!",
        "Weight": 4,
        "Id": 227
    },
    {
        "URL": "https://x.com/ecomarxi/status/1860078336422375519",
        "Date": "22/11/2024",
        "Text": "Democrats: We will always stand with Israel!\n\nOk, cool, let\u2019s just make sure you never take power again. You can\u2019t be the \u2018good guys\u2019 while supporting genocide, ethnic cleansing and apartheid. Let your demise make space for something that isn\u2019t a bunch of lies in a suit.",
        "Weight": 9,
        "Id": 234
    },
    {
        "URL": "https://x.com/Lowkey0nline/status/1860032949196063187",
        "Date": "22/11/2024",
        "Text": "Israel's largest arms firm Elbit Systems UK has lost the Watchkeeper drone contract worth over \u00a32 billion following years of Palestine Action targeting the Leicester factory working on the project.",
        "Weight": 8,
        "Id": 239
    },
    {
        "URL": "https://x.com/ecomarxi",
        "Date": "22/11/2024",
        "Text": "You\u2019re a bunch of fascist fucks who are so steeped in your own racism that \u2014 to alleviate some perceived guilt at one of your several previous genocides \u2014 you are committing another genocide.\n\nGermany clearly has no capacity for self-reflection, but that\u2019s exactly what you need!",
        "Weight": 10,
        "Id": 244
    },
    {
        "URL": "https://x.com/ecomarxi",
        "Date": "22/11/2024",
        "Text": "Don\u2019t you know? God is antisemitic! Nature is antisemitic! The truth is antisemitic! The laws of physics are all antisemitic, every last one! The whole damned universe is antisemitic!",
        "Weight": 15,
        "Id": 245
    },
    {
        "URL": "https://x.com/ecomarxi/status/1859971717411770783",
        "Date": "22/11/2024",
        "Text": "Western political commentators who do not frequently talk about the ongoing crimes against humanity that the West is committing in Gaza can not be taken seriously, since they reveal themselves to be nothing more than unofficial spokespeople of the Empire",
        "Weight": 6,
        "Id": 248
    },
    {
        "URL": "https://x.com/MothTongue_/status/1859941475423015385",
        "Date": "22/11/2024",
        "Text": "approximately 176k dollars needed for \n@munigaza\n's vital life-making infrastructure initiative! \n\nthe question still remains:\n \n\"ARE WE SERIOUS PEOPLE!?\"\n\nWE ONLY HAVE 32 DAYS \nTO FULFILL THIS, TO PROVE IT!!\n\nWE NEED **EVERY** VOICE NOW!!!\nhttps://gaza-city.ensany.com/campaign/6737",
        "Weight": 8,
        "Id": 252
    },
    {
        "URL": "https://x.com/ramapublishing/status/1859883226938147295",
        "Date": "22/11/2024",
        "Text": "The IOF should be a proscribed terrorist organisation. Now",
        "Weight": 5,
        "Id": 253
    },
    {
        "URL": "https://x.com/atlajala/status/1859600803788620294",
        "Date": "21/11/2024",
        "Text": "don't put faith in empire to indict itself. figureheads will fall, new ones will be installed. hands will be washed & they'll call it \"justice\" in order to continue genocide in other forms. these concessions are containment. there's no justice while isr*el & US empire exist.",
        "Weight": 5,
        "Id": 257
    },
    {
        "URL": "https://x.com/Jonathan_K_Cook/status/1859584750186299841",
        "Date": "21/11/2024",
        "Text": "No, President Herzog, the arrest warrants issued by the ICC for Netanyahu and Gallant today are not a \"dark day for humanity\".\n\nThey are the first, small ray of light we've had in 13 months of slaughter, ethnic cleansing, genocide.",
        "Weight": 5,
        "Id": 258
    },
    {
        "URL": "https://x.com/ecomarxi/status/1859921895338181088",
        "Date": "22/11/2024",
        "Text": "Switzerland maintained neutrality with the Nazis but they\u2019re like \u201cYeah fuck Netanyahu\u201d",
        "Weight": 4,
        "Id": 259
    },
    {
        "URL": "https://x.com/ecomarxi/status/1859921148915630195",
        "Date": "22/11/2024",
        "Text": "Don\u2019t you know? God is antisemitic! Nature is antisemitic! The truth is antisemitic! The laws of physics are all antisemitic, every last one! The whole damned universe is antisemitic!",
        "Weight": 15,
        "Id": 260
    },
    {
        "URL": "https://x.com/ecomarxi/status/1859920437515567374",
        "Date": "22/11/2024",
        "Text": "Peace depends on holding those responsible for these crimes accountable \u2014 both inside and outside of Israel.\n\nThere can be no justice without accountability, and there can be no peace without justice \u2014 that\u2019s just silencing the oppressed.\n\nWe must not stop until Palestine is free",
        "Weight": 15,
        "Id": 261
    },
    {
        "URL": "https://x.com/ecomarxi",
        "Date": "21/11/2024",
        "Text": "Keir Starmer: we are prepared to go to war to defend Israel\n\n[24 hours later]\n\nICC: *Issues arrest warrants for Israeli leaders for war crimes and crimes against humanity*\n\nHas there ever been a more corrupt Prime Minister of Britain?",
        "Weight": 26,
        "Id": 264
    },
    {
        "URL": "https://x.com/ecomarxi",
        "Date": "22/11/2024",
        "Text": "The Dreyfus trial was a false accusation of espionage.\n\nYou are a modern day Nazi who proudly told the world you were going to commit genocide, then did it, in front of the whole world.",
        "Weight": 7,
        "Id": 266
    },
    {
        "URL": "https://x.com/ecomarxi/status/1859750671576412453",
        "Date": "22/11/2024",
        "Text": "The Dreyfus trial was a false accusation of espionage.\n\nYou are a modern day Nazi who proudly told the world you were going to commit genocide, then did it, in front of the whole world.",
        "Weight": 7,
        "Id": 270
    },
    {
        "URL": "https://x.com/ecomarxi/status/1859727345755750511",
        "Date": "21/11/2024",
        "Text": "Journalists and people who work in the news media that aren\u2019t screaming about Gaza are all, every single one, our enemies. They are our appointed arbiters of truth and their silence on matters of such grave importance as genocide is a betrayal of all humanity.",
        "Weight": 9,
        "Id": 275
    },
    {
        "URL": "https://x.com/ecomarxi/status/1859725787383071047",
        "Date": "21/11/2024",
        "Text": "\u201cThe ICC is the legal wing of Hamas\u201d HAHAHAHAHAHAHAHA",
        "Weight": 4,
        "Id": 278
    },
    {
        "URL": "https://x.com/ecomarxi/status/1859710714467975358",
        "Date": "21/11/2024",
        "Text": "Keir Starmer: we are prepared to go to war to defend Israel\n\n[24 hours later]\n\nICC: *Issues arrest warrants for Israeli leaders for war crimes and crimes against humanity*\n\nHas there ever been a more corrupt Prime Minister of Britain?",
        "Weight": 26,
        "Id": 283
    },
    {
        "URL": "https://x.com/ecomarxi/status/1859711175149355500",
        "Date": "21/11/2024",
        "Text": "Oh \u2013 and the fact the Israelis pay him hundreds of thousands, of course!\n\nCheap fuck!",
        "Weight": 11,
        "Id": 285
    },
    {
        "URL": "https://x.com/ecomarxi",
        "Date": "21/11/2024",
        "Text": "Reminder: the ICC can issue arrest warrants for civilians who knowingly facilitate genocide.\n\nJournalists and media figureheads who have intentionally misled entire populations into support for genocide with known lies should suffer similar consequences.",
        "Weight": 10,
        "Id": 286
    },
    {
        "URL": "https://x.com/ecomarxi",
        "Date": "21/11/2024",
        "Text": "The ICC arrest warrants merely clarify what we have all known for years: it is impossible to uphold international law and support Israel",
        "Weight": 4,
        "Id": 290
    },
    {
        "URL": "https://x.com/ecomarxi/status/1859668897869463619",
        "Date": "21/11/2024",
        "Text": "Reminder: the ICC can issue arrest warrants for civilians who knowingly facilitate genocide.\n\nJournalists and media figureheads who have intentionally misled entire populations into support for genocide with known lies should suffer similar consequences.",
        "Weight": 10,
        "Id": 293
    },
    {
        "URL": "https://x.com/ecomarxi",
        "Date": "21/11/2024",
        "Text": "It\u2019s official: the British Government is supplying war criminals wanted by the World Court with weapons and running military operations to help them commit war crimes\n\nKeir Starmer and David Lammy must commit to a full arms embargo. NOW.",
        "Weight": 12,
        "Id": 295
    },
    {
        "URL": "https://x.com/sahouraxo/status/1859341799057392055",
        "Date": "20/11/2024",
        "Text": "\u201cIt is not a war.\u201d\n\n\u201cIt is full destruction.\u201d\n\n\u201cIt is GENOCIDE.\u201d\n\n\u2014UN Special Rapporteur, Francesca Albanese",
        "Weight": 5,
        "Id": 296
    },
    {
        "URL": "https://x.com/ecomarxi/status/1859667498234413210",
        "Date": "21/11/2024",
        "Text": "Yes, the US is a terrorist organisation",
        "Weight": 5,
        "Id": 297
    },
    {
        "URL": "https://x.com/ecomarxi",
        "Date": "20/11/2024",
        "Text": "Keir Starmer and David Lammy are genocidal war criminals guilty of the greatest crimes known to mankind.\n\nThis is what a vacuous centrist campaign will always deliver: the crimes of the Empire, on repeat.",
        "Weight": 4,
        "Id": 298
    },
    {
        "URL": "https://x.com/jeremycorbyn/status/1859626467837059195",
        "Date": "21/11/2024",
        "Text": "Following the ICC's arrest warrants, the Independent Alliance have written to the Prime Minister asking if he will comply with the ruling. \n\nThe UK government must decide: is it on the side of Israeli impunity or international law?",
        "Weight": 8,
        "Id": 299
    },
    {
        "URL": "https://x.com/ApsanaBegumMP/status/1859575956702171597",
        "Date": "21/11/2024",
        "Text": "The ICC have now issued arrest warrants for Benjamin Netayanhu and Yaov Gallant, for war crimes and crimes against humanity in Gaza.\n\nThe UK Government needs to get behind the ICC now, uphold international law and end its own complicity.",
        "Weight": 18,
        "Id": 304
    },
    {
        "URL": "https://x.com/HumzaYousaf/status/1859590143276880114",
        "Date": "21/11/2024",
        "Text": "The ICC has finally issued arrest warrants.\n\nPM must make an urgent statement confirming the UK will comply with international obligations. They must end all arm sales to Israel immediately and impose sanctions.\n\nIt is time those responsible for war crimes are held accountable.",
        "Weight": 16,
        "Id": 305
    },
    {
        "URL": "https://x.com/ecomarxi/status/1859617803256356960",
        "Date": "21/11/2024",
        "Text": "The ICC arrest warrants merely clarify what we have all known for years: it is impossible to uphold international law and support Israel",
        "Weight": 4,
        "Id": 307
    },
    {
        "URL": "https://x.com/ecomarxi/status/1859605327945027743",
        "Date": "21/11/2024",
        "Text": "It\u2019s official: the British Government is supplying war criminals wanted by the World Court with weapons and running military operations to help them commit war crimes\n\nKeir Starmer and David Lammy must commit to a full arms embargo. NOW.",
        "Weight": 12,
        "Id": 308
    },
    {
        "URL": "https://x.com/ecomarxi/status/1859559326551032096",
        "Date": "21/11/2024",
        "Text": "Are there any Zionists who don\u2019t love glorifying and defending rapists?",
        "Weight": 10,
        "Id": 311
    },
    {
        "URL": "https://x.com/ecomarxi/status/1859538551609729368",
        "Date": "21/11/2024",
        "Text": "This verified campaign for \n@moabuhabble\n is desperate for support.\n\nHe has an injured leg and needs medical assistance, as well as basic necessities for him and his family as they live under bombardment in Northern Gaza.\n\nPlease help if you can!",
        "Weight": 4,
        "Id": 312
    },
    {
        "URL": "https://x.com/mlkytee/status/1859434455540064470",
        "Date": "21/11/2024",
        "Text": "For those of you who aren\u2019t medical this is a man with a nasogastric tube in holding multiple bags that are draining his small bowel, surgical wounds and bladder and he, in that state, is being blindfolded & abducted from hospital by these Zionist scumbags. https://x.com/nadira_ali12/s/nadira_ali12/status/1859141470906970127\u2026",
        "Weight": 5,
        "Id": 313
    },
    {
        "URL": "https://x.com/ecomarxi/status/1859337661749829815",
        "Date": "20/11/2024",
        "Text": "Keir Starmer and David Lammy are genocidal war criminals guilty of the greatest crimes known to mankind.\n\nThis is what a vacuous centrist campaign will always deliver: the crimes of the Empire, on repeat.",
        "Weight": 4,
        "Id": 321
    },
    {
        "URL": "https://x.com/ecomarxi",
        "Date": "20/11/2024",
        "Text": "This family of 14 living in Khan Yunes in a tent are desperate for supplies amidst the Israeli siege.\n\nThis campaign has been verified by someone who knows the family and works with human rights bodies. Please support if you can!",
        "Weight": 8,
        "Id": 323
    },
    {
        "URL": "https://x.com/ecomarxi",
        "Date": "19/11/2024",
        "Text": "Palestine is a test of humanity. If you are comfortable seeing people herded into an open-air prison and brutalised and killed, or watching them have their lands and homes stolen by settlers, then you are an enemy of all humanity.\n\nThere but for the grace of God go any of us..",
        "Weight": 4,
        "Id": 328
    },
    {
        "URL": "https://x.com/MothTongue_/status/1859245053153079478",
        "Date": "20/11/2024",
        "Text": "approximately 179k dollars needed for \n@munigaza\n's vital life-making infrastructure initiative! \n\nthe question remains:\n \n\"ARE WE SERIOUS PEOPLE!?\"\n\nWE ONLY HAVE 34 DAYS \nTO FULFILL THIS AND PROVE IT!!\n\nWE NEED **EVERY** VOICE NOW!!!\n\nhttps://gaza-city.ensany.com/campaign/6737",
        "Weight": 8,
        "Id": 331
    },
    {
        "URL": "https://x.com/ecomarxi/status/1859258549068529696",
        "Date": "20/11/2024",
        "Text": "This family of 14 living in Khan Yunes in a tent are desperate for supplies amidst the Israeli siege.\n\nThis campaign has been verified by someone who knows the family and works with human rights bodies. Please support if you can!",
        "Weight": 8,
        "Id": 332
    },
    {
        "URL": "https://x.com/ecomarxi/status/1859222455794979022",
        "Date": "20/11/2024",
        "Text": "But the US would rather kill Palestinians than give its people cheap, reliable, clean, sustainable travel options",
        "Weight": 8,
        "Id": 334
    },
    {
        "URL": "https://x.com/ecomarxi",
        "Date": "19/11/2024",
        "Text": "There is political murmuring across the empire to crack down on boycotting Israel. The audacity of governments to attempt to force us into consuming products drenched in blood tells us one, very loud, very clear thing: BOYCOTTS WORK",
        "Weight": 4,
        "Id": 335
    },
    {
        "URL": "https://x.com/ecomarxi/status/1859193753363271769",
        "Date": "20/11/2024",
        "Text": "\u201cLooking for the hostages\u201d\n\nJesus Christ the stupidity of Zionists is INSANE",
        "Weight": 10,
        "Id": 338
    },
    {
        "URL": "https://x.com/moabuhabble/status/1859007172300206327",
        "Date": "19/11/2024",
        "Text": "Very hard night over Gaza tonight media isn\u2019t covering please pray for us",
        "Weight": 4,
        "Id": 343
    },
    {
        "URL": "https://x.com/ecomarxi/status/1859015484349575684",
        "Date": "19/11/2024",
        "Text": "Palestine is a test of humanity. If you are comfortable seeing people herded into an open-air prison and brutalised and killed, or watching them have their lands and homes stolen by settlers, then you are an enemy of all humanity.\n\nThere but for the grace of God go any of us..",
        "Weight": 4,
        "Id": 344
    },
    {
        "URL": "https://x.com/ecomarxi/status/1859013454163833295",
        "Date": "19/11/2024",
        "Text": "There is political murmuring across the empire to crack down on boycotting Israel. The audacity of governments to attempt to force us into consuming products drenched in blood tells us one, very loud, very clear thing: BOYCOTTS WORK",
        "Weight": 4,
        "Id": 346
    },
    {
        "URL": "https://x.com/ecomarxi/status/1859012010232737900",
        "Date": "19/11/2024",
        "Text": "You can tell Israel has no plan for \u2018the day after\u2019 because imagine a ceasefire in 1946 and Nazi Germany existing in the same state with Hitler and his high command still in place, no reasonable person is going to accept that or forget. Normalisation is done. Israel is cooked.",
        "Weight": 11,
        "Id": 347
    },
    {
        "URL": "https://x.com/MothTongue_/status/1858516502351134737",
        "Date": "18/11/2024",
        "Text": "approximately 181k dollars needed for \n@munigaza\n's vital life-making infrastructure initiative! \n\nthe question remains:\n \n\"ARE WE SERIOUS PEOPLE!?\"\n\nWE ONLY HAVE 36 DAYS \nTO FULFILL THIS AND PROVE IT!!\n\nWE NEED **EVERY** VOICE NOW!!!\n\nhttps://gaza-city.ensany.com/campaign/6737",
        "Weight": 8,
        "Id": 350
    },
    {
        "URL": "https://x.com/AsaWinstanley/status/1858661513961087054",
        "Date": "19/11/2024",
        "Text": "My latest scoop: Internal email shows the \n@nytimes\n killed its own journalist's investigation into Israeli mob violence in Amsterdam:",
        "Weight": 8,
        "Id": 353
    },
    {
        "URL": "https://x.com/ecomarxi/status/1858999051452383629",
        "Date": "19/11/2024",
        "Text": "No country helping Israel commit genocide has any authority on human rights or international law. They may subdue uprisings domestically with widespread propaganda, but this doesn\u2019t work on other heads of state. They have zero credibility now, less than zero. A circus of death.",
        "Weight": 9,
        "Id": 355
    },
    {
        "URL": "https://x.com/ecomarxi",
        "Date": "18/11/2024",
        "Text": "The British government is helping commit genocide without even having as much as a single debate in Parliament about its direct military involvement \u2014 never mind a vote \u2014 and you think we live in a democracy?\n\nARE YOU FUCKING OK?",
        "Weight": 5,
        "Id": 362
    },
    {
        "URL": "https://x.com/ecomarxi",
        "Date": "19/11/2024",
        "Text": "As well as the literal genocide, there is a cultural genocide taking place. While baby-killing soldiers are being protected so they can compete in European competitions, Palestinians are being culturally erased.\n\nThis is the anatomy of a coordinated genocide.",
        "Weight": 23,
        "Id": 363
    },
    {
        "URL": "https://x.com/ecomarxi/status/1858929956002070557",
        "Date": "19/11/2024",
        "Text": "The last Labour government committed historic war crimes.\n\nThis Labour government is doing the same.\n\nThere is no lesser evil \u2014 there is only evil, and resistance to it.",
        "Weight": 12,
        "Id": 364
    },
    {
        "URL": "https://x.com/ecomarxi/status/1858929169947648374",
        "Date": "19/11/2024",
        "Text": "Another day, another family in need.\n\nThis is a family of 14 living in Khan Yunes in a tent, desperate for supplies amidst the Israeli siege.\n\nThis campaign has been verified by someone who knows the family. Please support if you can!",
        "Weight": 8,
        "Id": 366
    },
    {
        "URL": "https://x.com/ecomarxi/status/1858918229126590690",
        "Date": "19/11/2024",
        "Text": "As well as the literal genocide, there is a cultural genocide taking place. While baby-killing soldiers are being protected so they can compete in European competitions, Palestinians are being culturally erased.\n\nThis is the anatomy of a coordinated genocide.",
        "Weight": 23,
        "Id": 368
    },
    {
        "URL": "https://x.com/ecomarxi",
        "Date": "19/11/2024",
        "Text": "Team Genocide, right!?",
        "Weight": 5,
        "Id": 372
    },
    {
        "URL": "https://x.com/ecomarxi",
        "Date": "19/11/2024",
        "Text": "Fuck off you war criminal. You\u2019re supporting Israel\u2019s illegal assault on Gaza which has killed tens of thousands of children and is in direct breach of the ICJ\u2019s measures, the Genocide Convention and many Int\u2019l Laws.\n\nEveryone is sick to fucking death of your RACIST hypocrisy.",
        "Weight": 13,
        "Id": 376
    },
    {
        "URL": "https://x.com/ecomarxi",
        "Date": "18/11/2024",
        "Text": "Western leaders cannot call what is occurring in Gaza a genocide because they are themselves all complicit. Just like a gang of thieves that can\u2019t admit the wrongdoing of the others without incriminating themselves, they are obliged by their guilt to lie to their last breath.",
        "Weight": 9,
        "Id": 379
    },
    {
        "URL": "https://x.com/Ema97n/status/1858675467110236186",
        "Date": "19/11/2024",
        "Text": "The thought that there're children in Gaza whose parents were both murdered by Israel\u2014along with their aunts, uncles, & every relative who could've cared for them, shatters my mind\u2014How is a child supposed to survive alone amidst starvation and constant bombings??(1/2)",
        "Weight": 8,
        "Id": 380
    },
    {
        "URL": "https://x.com/ecomarxi",
        "Date": "18/11/2024",
        "Text": "This verified campaign for \n@moabuhabble\n is desperate for support.\n\nHe has an injured leg and needs medical assistance, as well as basic necessities for him and his family as they live under bombardment in Northern Gaza.\n\nPlease help if you can!",
        "Weight": 4,
        "Id": 381
    },
    {
        "URL": "https://x.com/ecomarxi/status/1858663931834675442",
        "Date": "19/11/2024",
        "Text": "Palestine!",
        "Weight": 4,
        "Id": 382
    },
    {
        "URL": "https://x.com/caitoz/status/1858654208133919093",
        "Date": "18/11/2024",
        "Text": "Nothing Trump will do inside US borders over the next four years will be the tiniest fraction as murderous, tyrannical and worthy of ferocious opposition as what Biden is doing in Gaza right now.",
        "Weight": 4,
        "Id": 384
    },
    {
        "URL": "https://x.com/ecomarxi/status/1858659684875477099",
        "Date": "18/11/2024",
        "Text": "The British government is helping commit genocide without even having as much as a single debate in Parliament about its direct military involvement \u2014 never mind a vote \u2014 and you think we live in a democracy?\n\nARE YOU FUCKING OK?",
        "Weight": 5,
        "Id": 386
    },
    {
        "URL": "https://x.com/ecomarxi/status/1858657669348839596",
        "Date": "18/11/2024",
        "Text": "Western leaders cannot call what is occurring in Gaza a genocide because they are themselves all complicit. Just like a gang of thieves that can\u2019t admit the wrongdoing of the others without incriminating themselves, they are obliged by their guilt to lie to their last breath.",
        "Weight": 9,
        "Id": 388
    },
    {
        "URL": "https://x.com/ecomarxi/status/1858657098185212361",
        "Date": "18/11/2024",
        "Text": "There is no two ways about it: Keir Starmer and David Lammy are committing genocide, war crimes, and crimes against humanity",
        "Weight": 19,
        "Id": 389
    },
    {
        "URL": "https://x.com/ecomarxi/status/1858655358341832811",
        "Date": "18/11/2024",
        "Text": "This is literally what Dems did to anti-genocide protestors to attempt to obtain their votes, many of whom are People of Colour opposing a racist genocide. This quote is just so fucking perfect for this moment, depressingly.",
        "Weight": 10,
        "Id": 390
    },
    {
        "URL": "https://x.com/ecomarxi/status/1858652854246060387",
        "Date": "18/11/2024",
        "Text": "The same liberals that said they were gonna \u2018organise\u2019 after the election are deathly silent while Biden continues committing genocide. It\u2019s almost like they were just lying about opposing a genocide so they could manipulate people into voting for those committing that genocide.",
        "Weight": 15,
        "Id": 391
    },
    {
        "URL": "https://x.com/caitoz/status/1858645565506195642",
        "Date": "18/11/2024",
        "Text": "American progressives who stopped talking about Gaza in July-August to avoid hurting Kamala seem to have forgotten to go back to talking about Gaza now that the election is over.",
        "Weight": 8,
        "Id": 393
    },
    {
        "URL": "https://x.com/ecomarxi/status/1858605870269292545",
        "Date": "18/11/2024",
        "Text": "This verified campaign for \n@moabuhabble\n is desperate for support.\n\nHe has an injured leg and needs medical assistance, as well as basic necessities for him and his family as they live under bombardment in Northern Gaza.\n\nPlease help if you can!",
        "Weight": 4,
        "Id": 399
    },
    {
        "URL": "https://x.com/moabuhabble/status/1858577005320827383",
        "Date": "18/11/2024",
        "Text": "Death is everywhere in northern Gaza, pray for us",
        "Weight": 4,
        "Id": 400
    },
    {
        "URL": "https://x.com/ecomarxi",
        "Date": "17/11/2024",
        "Text": "Do not stop speaking out about the genocide. It still continues night & day. Even if the feed is not showing you the corpses, they still exist. Seek out news if you must & be the voice sharing what is happening. We must keep Gaza at the top of the feed until Palestine is free!",
        "Weight": 13,
        "Id": 402
    },
    {
        "URL": "https://x.com/kennardmatt/status/1858463374666846680",
        "Date": "18/11/2024",
        "Text": "Al Jazeera finds the UK has flown nearly half the reconnaissance missions over Gaza since the genocide began.\n\nThis is more than double Israel itself.\n\nBritain is a participant and leads in providing intelligence for the genocide.\n\nThis has never been reported in a UK newspaper.",
        "Weight": 18,
        "Id": 403
    },
    {
        "URL": "https://x.com/Ema97n/status/1858320528299221389",
        "Date": "18/11/2024",
        "Text": "Israel was built on the blood of Palestinians\u2014The claim of \"a land without a people for a people without a land\" was nothing but a myth\u2014Now, Israel is repeating the same tactic by alleging that northern Gaza is empty of people\u2014(1/2)",
        "Weight": 20,
        "Id": 404
    },
    {
        "URL": "https://x.com/ecomarxi",
        "Date": "17/11/2024",
        "Text": "Feminism that doesn\u2019t include Palestinian women and girls isn\u2019t any feminism that\u2019s worth a damn",
        "Weight": 4,
        "Id": 407
    },
    {
        "URL": "https://x.com/MothTongue_/status/1858172593229926730",
        "Date": "17/11/2024",
        "Text": " THIS IS URGENT  \n\napproximately 182.4k dollars needed for \n@munigaza\n's vital life-making infrastructure initiative! \n\nthe question remains:\n \n\"ARE WE SERIOUS PEOPLE!?\"\n\nWE HAVE 37 DAYS \nTO FULFILL THIS AND PROVE IT!!\n\nWE NEED **EVERY** VOICE NOW!!!\nhttps://gaza-city.ensany.com/campaign/6737",
        "Weight": 8,
        "Id": 408
    },
    {
        "URL": "https://x.com/ecomarxi/status/1858287487086367048",
        "Date": "17/11/2024",
        "Text": "Do not stop speaking out about the genocide. It still continues night & day. Even if the feed is not showing you the corpses, they still exist. Seek out news if you must & be the voice sharing what is happening. We must keep Gaza at the top of the feed until Palestine is free!",
        "Weight": 13,
        "Id": 410
    },
    {
        "URL": "https://x.com/ecomarxi/status/1858284063301185827",
        "Date": "17/11/2024",
        "Text": "Please support this verified campaign if you can!\n\nMohammed is injured, living in Northern Gaza where aid and food is scarce, taking care of his family \u2014 he needs all the help we can give him!",
        "Weight": 4,
        "Id": 411
    },
    {
        "URL": "https://x.com/ecomarxi/status/1858266611792113758",
        "Date": "17/11/2024",
        "Text": "Unless you say it about a Palestinian child, in which case the fascist fucks on content moderation just shrug",
        "Weight": 4,
        "Id": 415
    },
    {
        "URL": "https://x.com/ecomarxi",
        "Date": "16/11/2024",
        "Text": " Urgent  \n\nMohammed is in northern Gaza amidst famine and scarce medical aid, and he is seriously injured in his leg and needs specialized surgery, all while caring for his family.\n\nPlease help him support his family. North Gazans need our help!",
        "Weight": 8,
        "Id": 417
    },
    {
        "URL": "https://x.com/ecomarxi",
        "Date": "16/11/2024",
        "Text": "Israel is committing genocide. Everyone knows this. Those that deny it are complicit.",
        "Weight": 9,
        "Id": 418
    },
    {
        "URL": "https://x.com/ecomarxi",
        "Date": "16/11/2024",
        "Text": "Zionists: *gang rape Palestinians to death, laugh about sniper-firing children, commit every crime known to mankind*\n\nPeople: This must end\n\nWestern leaders: ISRAEL HAS A RIGHT TO DEFEND ITSELF\n\n[same day]\n\nWestern leaders: We are beacons of equality, human rights and rule of law",
        "Weight": 22,
        "Id": 419
    },
    {
        "URL": "https://x.com/ecomarxi/status/1858229609705210250",
        "Date": "17/11/2024",
        "Text": "FIFA is forcing the Israeli football team into European football while ignoring Israel\u2019s crimes, including hospitalising football players from other teams. The betrayal is massive. Our cultural institutions are choosing Israeli genocide over the people. They are complicit.",
        "Weight": 27,
        "Id": 424
    },
    {
        "URL": "https://x.com/ecomarxi/status/1858228560609304944",
        "Date": "17/11/2024",
        "Text": "While Israel plays Belgium in the UEFA Nations League, a competition for EUROPEAN teams, Celine Haidar, a Lebanese national football player, lies in intensive care, seriously injured by an Israeli attack on civilians in Beirut.\n\n\n@FIFAcom\n is complicit",
        "Weight": 12,
        "Id": 425
    },
    {
        "URL": "https://x.com/ecomarxi/status/1858224282154766619",
        "Date": "17/11/2024",
        "Text": "Feminism that doesn\u2019t include Palestinian women and girls isn\u2019t any feminism that\u2019s worth a damn",
        "Weight": 4,
        "Id": 426
    },
    {
        "URL": "https://x.com/ReemWheat/status/1858180110047973727",
        "Date": "17/11/2024",
        "Text": "This genocide is a North American issue, it is not a distant issue in middle east only, do not deceive yourself: your policy,arms,tax money, media all are used in genocide service. Silencing is huge. In North American you are serving a genocide, you are not an innocent stand by!",
        "Weight": 15,
        "Id": 428
    },
    {
        "URL": "https://x.com/ecomarxi",
        "Date": "16/11/2024",
        "Text": "Our role, as the first generation in history to witness a live-streamed genocide, is to ensure that we are also the last. The evidence of Western complicity & criminality cannot be overstated. The lies at the heart of our society have collapsed: we must ensure they lead to change",
        "Weight": 5,
        "Id": 431
    },
    {
        "URL": "https://x.com/Alqawasmi_Rula/status/1858036855469420929",
        "Date": "17/11/2024",
        "Text": "The Genocide is continuous.",
        "Weight": 5,
        "Id": 432
    },
    {
        "URL": "https://x.com/ecomarxi/status/1857928349382746510",
        "Date": "16/11/2024",
        "Text": "If you have journalist friends, you need to ask them what they\u2019ve said and done about Gaza in their respective institutions. If they haven\u2019t said or done much, they\u2019re the enemy. They\u2019ve chosen the comfort of quiet complicity over their duty as journalists. They serve evil now.",
        "Weight": 4,
        "Id": 435
    },
    {
        "URL": "https://x.com/ecomarxi/status/1857926928327463229",
        "Date": "16/11/2024",
        "Text": "Zionists: *gang rape Palestinians to death, laugh about sniper-firing children, commit every crime known to mankind*\n\nPeople: This must end\n\nWestern leaders: ISRAEL HAS A RIGHT TO DEFEND ITSELF\n\n[same day]\n\nWestern leaders: We are beacons of equality, human rights and rule of law",
        "Weight": 22,
        "Id": 437
    },
    {
        "URL": "https://x.com/ecomarxi/status/1857923934638813580",
        "Date": "16/11/2024",
        "Text": "Israel is committing genocide. Everyone knows this. Those that deny it are complicit.",
        "Weight": 9,
        "Id": 439
    },
    {
        "URL": "https://x.com/ecomarxi",
        "Date": "16/11/2024",
        "Text": "Fuck off you racist cunt, the sooner Canada turns its back on charlatans like you who feign concern for equality and human rights while facilitating genocide and colonialism, the better.\n\nYou are the very worst of us \u2014 because you speak of justice while acting with malice.",
        "Weight": 5,
        "Id": 441
    },
    {
        "URL": "https://x.com/ecomarxi/status/1857921031064662116",
        "Date": "16/11/2024",
        "Text": " Urgent  \n\nMohammed is in northern Gaza amidst famine and scarce medical aid, and he is seriously injured in his leg and needs specialized surgery, all while caring for his family.\n\nPlease help him support his family. North Gazans need our help!",
        "Weight": 8,
        "Id": 442
    },
    {
        "URL": "https://x.com/chai_zaferooni/status/1857845027986149646",
        "Date": "16/11/2024",
        "Text": "Please continue to support Mohammed and his family in north Gaza. Mohammed cannot stand because of an injury in his leg that requires a specialized surgery. His fundraiser has slowed a lot lately. He really needs the support. Please share his post & follow him.",
        "Weight": 4,
        "Id": 443
    },
    {
        "URL": "https://x.com/chai_zaferooni/status/1857621503241551954",
        "Date": "16/11/2024",
        "Text": "Mohammed is seriously injured in his leg and needs specialized surgery. He\u2019s not able to stand. He is in north Gaza as well, where famine and medicine is more scarce. His fundraiser has stagnated too. Please help him support his family. North Gazans need our help.",
        "Weight": 8,
        "Id": 444
    },
    {
        "URL": "https://x.com/ecomarxi/status/1857915832396882390",
        "Date": "16/11/2024",
        "Text": "Our role, as the first generation in history to witness a live-streamed genocide, is to ensure that we are also the last. The evidence of Western complicity & criminality cannot be overstated. The lies at the heart of our society have collapsed: we must ensure they lead to change",
        "Weight": 5,
        "Id": 445
    },
    {
        "URL": "https://x.com/ecomarxi/status/1857905069737586849",
        "Date": "16/11/2024",
        "Text": " Urgent Campaign \n\nThis campaign is for families with NO PHONE and therefore NO CAMPAIGN \u2014 these are some of the most desperate people in Gaza right now, where basic items are hundreds of dollars!\n\nPlease help if you are able to!\n\n",
        "Weight": 4,
        "Id": 447
    },
    {
        "URL": "https://x.com/ecomarxi",
        "Date": "14/11/2024",
        "Text": "The word Zionist is now means gang-raping, baby-killing coward.\n\nWhen someone says they are a Zionist, this is what they support: gang-rape and murdering children.\n\nThere is no other definition.",
        "Weight": 10,
        "Id": 449
    },
    {
        "URL": "https://x.com/afshinrattansi/status/1857041910642180407",
        "Date": "14/11/2024",
        "Text": "JULIAN ASSANGE: \u2018Artificial intelligence is being used for mass assassinations in Gaza\u2019 \n\n\u201cThe majority of targets in Gaza are bombed as a result of artificial intelligence targeting.\u201d \n\nThe US, UK, EU and Israel have created an AI dystopia. \n\nhttps://youtu.be/dQCM9QTNNso?si=g5URAFi0diqybTuK\u2026",
        "Weight": 12,
        "Id": 450
    },
    {
        "URL": "https://x.com/ecomarxi/status/1857378711114285147",
        "Date": "15/11/2024",
        "Text": "Soldiers singing about committing genocide.\n\nEither humanity ends, or this is seen as the worst humanity ever reached in retrospect.",
        "Weight": 5,
        "Id": 453
    },
    {
        "URL": "https://x.com/ecomarxi/status/1857180080843186278",
        "Date": "14/11/2024",
        "Text": "The word Zionist is now means gang-raping, baby-killing coward.\n\nWhen someone says they are a Zionist, this is what they support: gang-rape and murdering children.\n\nThere is no other definition.",
        "Weight": 10,
        "Id": 457
    },
    {
        "URL": "https://x.com/MothTongue_/status/1857131824667066789",
        "Date": "14/11/2024",
        "Text": " THIS IS URGENT  \n\napproximately 186.5k dollars needed for \n@munigaza\n's vital life-making infrastructure initiative! \n\nthe question remains:\n \n\"ARE WE SERIOUS PEOPLE!?\"\n\nWE HAVE 40 DAYS \nTO FULFILL THIS AND PROVE IT!!\n\nWE NEED **EVERY** VOICE NOW!!!\n\nhttps://gaza-city.ensany.com/campaign/6737",
        "Weight": 8,
        "Id": 458
    },
    {
        "URL": "https://x.com/PopBase/status/1857074933945307176",
        "Date": "14/11/2024",
        "Text": "Ben & Jerry\u2019s has sued its parent company Unilever for allegedly silencing its attempts to express support for Palestinian refugees and threatening to dismantle its board and sue its members over the issue. (Reuters)",
        "Weight": 4,
        "Id": 459
    },
    {
        "URL": "https://x.com/ecomarxi/status/1857169854341468516",
        "Date": "14/11/2024",
        "Text": "The chief prosecutor of the ICC requested warrants for the obvious and blatant war crimes Israel has committed.\n\nThe ICC responded by stifling the requests and launching an investigation into him.\n\nThe US Empire is on full, glaring, disgusting display.",
        "Weight": 16,
        "Id": 460
    },
    {
        "URL": "https://x.com/ecomarxi",
        "Date": "14/11/2024",
        "Text": " Urgent Campaign \n\nThis campaign is for families with NO PHONE and therefore NO CAMPAIGN \u2014 these are some of the most desperate people in Gaza right now, where basic items are hundreds of dollars!\n\nPlease help if you are able to!\n\n",
        "Weight": 4,
        "Id": 463
    },
    {
        "URL": "https://x.com/declassifiedUK/status/1856623870272307387",
        "Date": "13/11/2024",
        "Text": " NEW -- UK exported parts for Israeli air force after suspending arms sales \n\nby \n@jmcevoy_2\n \n\nExclusive: Cargo documents show how British-made aircraft components were shipped to Israel last month.",
        "Weight": 12,
        "Id": 464
    },
    {
        "URL": "https://x.com/ecomarxi/status/1857007213836960105",
        "Date": "14/11/2024",
        "Text": " Urgent Campaign \n\nThis campaign is for families with NO PHONE and therefore NO CAMPAIGN \u2014 these are some of the most desperate people in Gaza right now, where basic items are hundreds of dollars!\n\nPlease help if you are able to!\n\n",
        "Weight": 4,
        "Id": 465
    },
    {
        "URL": "https://x.com/ecomarxi",
        "Date": "13/11/2024",
        "Text": "My criticism weighed heavily on the Democrats because the Democrats were in power and committing genocide.\n\nMy criticism will move towards Trump because Trump will be in power and committing genocide soon.\n\nOpposing genocide is not a partisan act.",
        "Weight": 15,
        "Id": 469
    },
    {
        "URL": "https://x.com/DrJillStein/status/1856475146430886053",
        "Date": "12/11/2024",
        "Text": "As expected, the Biden-Harris admin's \"warning\" to Israel to stop blocking aid to Gaza or face consequences was just empty words from habitual liars.\n\nIsrael is STILL blocking aid & Biden-Harris arming the genocide is STILL illegal under US law.\n\nWe demand a weapons embargo NOW!",
        "Weight": 17,
        "Id": 471
    },
    {
        "URL": "https://x.com/Ema97n/status/1856664665389924572",
        "Date": "13/11/2024",
        "Text": "This is the 'Israel has a right to defend itself'\u2014its burning innocent people alive.. https://x.com/SuppressedNws//SuppressedNws/status/1856443487018688652\u2026",
        "Weight": 4,
        "Id": 472
    },
    {
        "URL": "https://x.com/Lowkey0nline/status/1856452685463204236",
        "Date": "12/11/2024",
        "Text": "\"There is no such thing as the West Bank, it's Judea and Samaria...\"\n\nTrump's new ambassador to the UN. It looks very likely he is getting ready to recognise the West Bank as part of Israel.",
        "Weight": 4,
        "Id": 475
    },
    {
        "URL": "https://x.com/ecomarxi",
        "Date": "13/11/2024",
        "Text": " Urgent Campaign \n\nThis campaign is for families with NO PHONE and therefore NO CAMPAIGN \u2014 these are some of the most desperate people in Gaza right now, where basic food items are hundreds of dollars!\n\nPlease help if you are able to!\n\n",
        "Weight": 4,
        "Id": 476
    },
    {
        "URL": "https://x.com/MothTongue_/status/1856700997415903730",
        "Date": "13/11/2024",
        "Text": " THIS IS URGENT  \n\napproximately 187k dollars needed for \n@munigaza\n's vital life-making infrastructure initiative! \n\nthe question remains:\n \n\"ARE WE SERIOUS PEOPLE!?\"\n\nWE HAVE 41 DAYS \nTO FULFILL THIS AND PROVE IT!!\n\nWE NEED **EVERY** VOICE NOW!!!\n\nhttps://gaza-city.ensany.com/campaign/6737",
        "Weight": 8,
        "Id": 480
    },
    {
        "URL": "https://x.com/ecomarxi/status/1856750721481261077",
        "Date": "13/11/2024",
        "Text": "My criticism weighed heavily on the Democrats because the Democrats were in power and committing genocide.\n\nMy criticism will move towards Trump because Trump will be in power and committing genocide soon.\n\nOpposing genocide is not a partisan act.",
        "Weight": 15,
        "Id": 481
    },
    {
        "URL": "https://x.com/ecomarxi/status/1856749908478628261",
        "Date": "13/11/2024",
        "Text": "If you endorsed Harris while claiming you were gonna \u2018organise under Harris\u2019 to tackle her stance on Gaza, then you should also be organising under Trump, because if your opposition to genocide was truly genuine, it would not depend on whether your team won",
        "Weight": 9,
        "Id": 483
    },
    {
        "URL": "https://x.com/ecomarxi/status/1856732479106789885",
        "Date": "13/11/2024",
        "Text": " Urgent Campaign \n\nThis campaign is for families with NO PHONE and therefore NO CAMPAIGN \u2014 these are some of the most desperate people in Gaza right now, where basic food items are hundreds of dollars!\n\nPlease help if you are able to!\n\n",
        "Weight": 4,
        "Id": 484
    },
    {
        "URL": "https://x.com/ecomarxi/status/1856679967779655766",
        "Date": "13/11/2024",
        "Text": "\u201cYale is no different from Hamas,\u201d written by Bullshitter Bill here, is, in a single sentence, an encapsulation of the madness that has consumed America at the alter of its relentless insistence that it somehow has the divine right to steal land and massacre civilians freely.",
        "Weight": 4,
        "Id": 485
    },
    {
        "URL": "https://x.com/ecomarxi/status/1856643178184520031",
        "Date": "13/11/2024",
        "Text": " Campaign for Gaza \n\nThis campaign is for families with NO PHONE and NO CAMPAIGN \u2014 some of the most desperate people in Gaza right now, where basic items are hundreds of dollars!\n\nPlease help if you are able to! Video below from CAD in Gaza!\n\n\n\nhttps://gofund.me/191e529d",
        "Weight": 12,
        "Id": 487
    },
    {
        "URL": "https://x.com/ecomarxi/status/1856628686125969518",
        "Date": "13/11/2024",
        "Text": "Musk\u2019s \u2018Free Speech\u2019 platform has been suspending the accounts of Palestinians who oppose the genocide of their people.\n\nNew account of below for mutuals: \n@PaliGnosis",
        "Weight": 13,
        "Id": 489
    },
    {
        "URL": "https://x.com/PaliGnosis/status/1855864575461367913",
        "Date": "11/11/2024",
        "Text": "This will be my new home till I get my account back. Thank you everyone for the support and love. \nNo jew is silencing me or the truth. #freePalestine ",
        "Weight": 6,
        "Id": 490
    },
    {
        "URL": "https://x.com/ecomarxi",
        "Date": "12/11/2024",
        "Text": "FIFA: Show racism the red card!\n\nZionists: Here\u2019s a bunch of cash\n\nFIFA: Woo! Racism is good! Fascism, too! Even racist genocides! Come on in, kill some kids in the stands if you want to! Anything goes!",
        "Weight": 15,
        "Id": 494
    },
    {
        "URL": "https://x.com/ecomarxi",
        "Date": "12/11/2024",
        "Text": "UEFA is forcing European teams to play in different locations to accommodate Israel\u2019s genocidal fans instead of doing the right thing and banning Israeli teams from all UEFA competitions at both domestic and international level. There are cowards running everything.",
        "Weight": 12,
        "Id": 495
    },
    {
        "URL": "https://x.com/MothTongue_/status/1863945664272400862",
        "Date": "03/12/2024",
        "Text": "approximately 163.5k dollars needed for \n@munigaza\n's vital life-making infrastructure initiative! \n\nthe question STILL remains:\n \n\"ARE WE SERIOUS PEOPLE!?\"\n\nWE ONLY HAVE 21 DAYS \nTO FULFILL THIS, TO PROVE IT!!\n\nWE STILL NEED \n**EVERY** \nVOICE NOW!!! \n\nhttps://gaza-city.ensany.com/campaign/6737",
        "Weight": 8,
        "Id": 496
    },
    {
        "URL": "https://x.com/ecomarxi",
        "Date": "03/12/2024",
        "Text": " ALL DONATIONS DOUBLED \n\nThis campaign is for people in Gaza without campaigns \u2014 and GlobalGiving will match any donations made until midnight tonight!\n\nThat means all donations are doubled!\n\nPlease donate if you can!\n\nhttps://gofund.me/a385b712",
        "Weight": 4,
        "Id": 497
    }
]